{
    "rtl": true,
    "id": "he_IL",
    "lang": "Hebrew",
    "native": "עברית",
    "Yes": "כן",
    "No": "לא",
    "Projects": "פרויקטים",
    "System Monitor": "מוניטור מערכת",
    "AiPanic": "AiPanic",
    "Settings": "הגדרות",
    "About": "אודות",
    "Check for Update": "בדיקת עדכון",
    "None": "אין",
    "Installed": "מותקן",
    "Install": "התקנה",
    "Launch": "הפעלה",
    "Uninstall": "הסרת התקנה",
    "Update": "עדכון",
    "Delete venv": "מחיקת venv",
    "Create venv": "יצירת venv",
    "Installed Version": "גרסה מותקנת",
    "Installing and launching": "מתקין ומפעיל",
    "Launching": "מפעיל",
    "Launched": "הופעל",
    "Pre installed": "מותקן מראש",
    "Use pre installed": "שימוש בגרסה המותקנת מראש",
    "Arguments": "ארגומנטים",
    "Setup": "פעולות",
    "Custom": "התאמה אישית",
    "Download Models": "הורדת מודלים",
    "Update available": "עדכון זמין",
    "No update available - latest version": "אין עדכון זמין - הגרסה האחרונה",
    "Could not find version information": "לא ניתן למצוא מידע על גרסה",
    "CPU Usage": "שימוש במעבד",
    "RAM Usage": "שימוש בזיכרון",
    "Temperature": "טמפרטורה",
    "VRAM Usage": "שימוש בVRAM",
    "Power Usage": "שימוש בכוח",
    "Don't forget to leave a like/star.": "אל תשכחו להשאיר לייק/כוכב",
    "isIncomplete": ".הפרויקט ניסיוני במתקין. אם אינכם רוצים להתמודד עם שגיאות, מומלץ לדלג כרגע",
    "Download": "להוריד",
    "set_custom_project_path": "הגדרת נתיב הפרוייקט",
    "If_not_activated": "אם לא מופעל",
    "will_be_used": "ישומש",
    "browse": "עיון",
    "set_path": "קביעת נתיב",
    "activate": "הפעלה",
    "activated": "מופעל",
    "check_python_path": "חשוב! ודאו שסימנתם את הוספת Python 3.10 ל- PATH לפני ההתקנה.",
    "add_project_name_folder_to_path": "הוספת שם תיקיית הפרוייקט לנתיב",
    "save": "שמירה",
    "quick_Launch": "הפעלה מהירה",
    "path_spaces_warning": "אזהרה: רווחים בנתיב עלולים לגרום לבעיות במהלך ההתקנה. שיקלו להשתמש בנתיב ללא רווחים או לקצר את אורך הנתיב."
}