{
    "rtl": false,
    "id": "it_IT",
    "lang": "Italian",
    "native": "italiano",
    "Yes": "Sì",
    "No": "No",
    "Download Models": "Scarica modelli",
    "Projects": "Progetti",
    "System Monitor": "Monitor di sistema",
    "AiPanic": "AiPanic",
    "Settings": "Impostazioni",
    "About": "Informazioni",
    "Check for Update": "Verifica aggiornamenti",
    "None": "Nessuno",
    "Installed": "Installato",
    "Install": "Installa",
    "Launch": "Avvia",
    "Uninstall": "Disinstalla",
    "Update": "Aggiorna",
    "Delete venv": "Elimina venv",
    "Create venv": "Crea venv",
    "Installed Version": "Versione installata",
    "Installing and launching": "Installazione e avvio",
    "Launching": "Avvio in corso",
    "Launched": "Avviato",
    "Pre installed": "Pre-installato",
    "Use pre installed": "Usa pre-installato",
    "Arguments": "Argomenti",
    "Setup": "Azioni",
    "Custom": "Personalizzata",
    "Update available": "Aggiornamento disponibile",
    "No update available - latest version": "Nessun aggiornamento disponibile - ultima versione",
    "Could not find version information": "Impossibile trovare informazioni sulla versione",
    "CPU Usage": "Utilizzo CPU",
    "RAM Usage": "Utilizzo RAM",
    "Temperature": "Temperatura",
    "VRAM Usage": "Utilizzo VRAM",
    "Power Usage": "Utilizzo energia",
    "Don't forget to leave a like/star.": "Non dimenticare di lasciare un like/stella.",
    "isIncomplete": "Questo progetto non è stato completamente implementato nell'installatore. Se non si desidera occuparsi di errori, è consigliabile saltarlo per ora.",
    "Download": "Scaricare",
    "set_custom_project_path": "Imposta percorso personalizzato del progetto",
    "If_not_activated": "Se non attivato",
    "will_be_used": "sarà utilizzato",
    "browse": "Navigare",
    "set_path": "Imposta percorso",
    "activate": "Attiva",
    "activated": "Attivato",
    "check_python_path": "IMPORTANTE! Assicurati di selezionare 'Aggiungi Python 3.10 al PATH' prima di procedere con l'installazione.",
    "add_project_name_folder_to_path": "Aggiungi il nome della cartella del progetto al PATH"
}