{
    "rtl": false,
    "id": "pt_BR",
    "lang": "Brazilian Portuguese",
    "native": "Português",
    "Yes": "Sim",
    "No": "Não",
    "Download Models": "Baixar modelos",
    "Projects": "Projetos",
    "System Monitor": "Monitor do sistema",
    "AiPanic": "AiPanic",
    "Settings": "Configurações",
    "About": "Sobre",
    "Check for Update": "Verificar atualização",
    "None": "Nenhum",
    "Installed": "Instalado",
    "Install": "Instalar",
    "Launch": "Iniciar",
    "Uninstall": "Desinstalar",
    "Update": "Atualizar",
    "Delete venv": "Excluir venv",
    "Create venv": "Criar venv",
    "Installed Version": "Versão instalada",
    "Installing and launching": "Instalando e iniciando",
    "Launching": "Iniciando",
    "Launched": "Iniciado",
    "Pre installed": "Pré-instalado",
    "Use pre installed": "Usar pré-instalado",
    "Arguments": "Argumentos",
    "Setup": "Ações",
    "Custom": "Personalizado",
    "Update available": "Atualização disponível",
    "No update available - latest version": "Não há atualizações disponíveis - última versão",
    "Could not find version information": "Não foi possível encontrar informações de versão",
    "CPU Usage": "Uso de CPU",
    "RAM Usage": "Uso de RAM",
    "Temperature": "Temperatura",
    "VRAM Usage": "Uso de VRAM",
    "Power Usage": "Uso de energia",
    "Don't forget to leave a like/star.": "Não esqueça de deixar um like/estrela.",
    "isIncomplete": "Este projeto não foi totalmente implementado no instalador. Se você não quiser lidar com erros, é recomendável pular este por enquanto.",
    "Download": "Baixar"
}