{
    "rtl": false,
    "id": "tr_TR",
    "lang": "Turkish",
    "native": "Türkçe",
    "Yes": "Evet",
    "No": "Hayır",
    "Download Models": "Modelleri İndir",
    "Projects": "Projeler",
    "System Monitor": "Sistem İzleme",
    "AiPanic": "AiPanic",
    "Settings": "Ayarlar",
    "About": "Hakkında",
    "Check for Update": "Güncellemeleri Kontrol Et",
    "None": "Hiçbiri",
    "Installed": "Yüklü",
    "Install": "Yükle",
    "Launch": "Başlat",
    "Uninstall": "Kaldır",
    "Update": "Güncelle",
    "Delete venv": "venv Sil",
    "Create venv": "venv Oluştur",
    "Installed Version": "Yüklü Sürüm",
    "Installing and launching": "Yükleme ve başlatma",
    "Launching": "Başlatılıyor",
    "Launched": "Başlatıldı",
    "Pre installed": "Önceden yüklenmiş",
    "Use pre installed": "Önceden yüklenmiş olanı kullan",
    "Arguments": "Argümanlar",
    "Setup": "Kurulum",
    "Custom": "Özel",
    "Update available": "Güncelleme mevcut",
    "No update available - latest version": "Güncelleme mevcut değil - en son sürüm",
    "Could not find version information": "Sürüm bilgisi bulunamadı",
    "CPU Usage": "CPU Kullanımı",
    "RAM Usage": "RAM Kullanımı",
    "Temperature": "Sıcaklık",
    "VRAM Usage": "VRAM Kullanımı",
    "Power Usage": "Güç Kullanımı",
    "Don't forget to leave a like/star.": "Beğenmeyi/yıldızlamayı unutmayın.",
    "isIncomplete": "Bu proje, kurulumda tamamen uygulanmadı. Hatalarla uğraşmak istemiyorsanız şimdilik atlamayı öneriyoruz."
}